{
    "基础信息": {
        "住院号": 583388,
        "条码号": 20757249800,
        "序号": 1094
    },
    "图片路径": "../acute_arms/1094.png",
    "临床": {
        "发热": 1,
        "关节及骨骼痛": 1,
        "出血": 0,
        "贫血": 0,
        "器官肿大": 1,
        "中枢神经系统症状": 1,
        "腹痛": 0,
        "咳嗽": 0,
        "皮疹": 0
    },
    "生化": {
        "乳酸脱氢酶LDH": 3680.0,
        "铁蛋白Fer": 924.77
    },
    "血常规报告参数": {
        "性别(男1女2）": 2.0,
        "年龄": 5.3,
        "WBC(109/L)": 13.6,
        "RBC(1012/L)": 3.63,
        "HGB(g/L)": 93.0,
        "HCT(％）": 28.9,
        "MCV(fL)": 79.6,
        "MCH(pg)": 25.6,
        "MCHC(g/L)": 322.0,
        "PLT(109/L)": 91.0,
        "RDW-SD(fL)": 38.3,
        "RDW-CV(％）": 13.4,
        "PDW（fL)": 8.8,
        "MPV(fL)": 10.2,
        "P-LCR(％）": 24.2,
        "PCT(％）": 0.09,
        "NRBC﹟(109/L)": 0.59,
        "NRBC％（/100WBC)": 4.3,
        "NEUT％": 28.3,
        "LYMPH％": 50.5,
        "MONO％": 20.4,
        "EO％": 0.3,
        "BASO％": 0.5,
        "IG﹟(109/L)": 0.74,
        "IG％": 5.4
    },
    "淋巴类别": {
        "Blasts/Abn Ly": 260.0,
        "Atypical": 0.0,
        "Atypical.1": 0.0,
        "Blasts": 0.0,
        "Abn Ly": 0.0
    },
    "血常规通道参数": {
        "WNR-X": 169.7,
        "WNR-Y": 102.0,
        "WNR-Z": 87.9,
        "WPC-X": 67.2,
        "WPC-Y": 175.2,
        "WPC-Z": 80.0,
        "HFLC%": 0.4,
        "WBC": 13.71,
        "NE-SSC": 138.7,
        "NE-SFL": 49.9,
        "NE-FSC": 85.9,
        "LY-X": 87.0,
        "LY-Y": 66.7,
        "LY-Z": 60.2,
        "MO-X": 109.3,
        "MO-Y": 93.4,
        "MO-Z": 67.6,
        "NE-WX": 476.0,
        "NE-WY": 1302.0,
        "NE-WZ": 745.0,
        "LY-WX": 563.0,
        "LY-WY": 1034.0,
        "LY-WZ": 615.0,
        "MO-WX": 302.0,
        "MO-WY": 124.0,
        "MO-WZ": 665.0
    },
    "镜检": 13,
    "label": 0
}