{
    "基础信息": {
        "住院号": 606828.0,
        "条码号": 20993473600.0,
        "序号": 1294.0
    },
    "图片路径": "../acute_arms/1294.png",
    "临床": null,
    "生化": null,
    "血常规报告参数": {
        "性别(男1女2）": 1.0,
        "年龄": 13.9,
        "WBC(109/L)": 2.64,
        "RBC(1012/L)": 3.35,
        "HGB(g/L)": 93.0,
        "HCT(％）": 30.0,
        "MCV(fL)": 89.6,
        "MCH(pg)": 27.8,
        "MCHC(g/L)": 310.0,
        "PLT(109/L)": 121.0,
        "RDW-SD(fL)": 49.5,
        "RDW-CV(％）": 16.7,
        "PDW（fL)": 11.8,
        "MPV(fL)": 11.3,
        "P-LCR(％）": 31.1,
        "PCT(％）": 0.14,
        "NRBC﹟(109/L)": 0.1,
        "NRBC％（/100WBC)": 3.8,
        "NEUT％": 26.8,
        "LYMPH％": 52.3,
        "MONO％": 20.5,
        "EO％": 0.0,
        "BASO％": 0.4,
        "IG﹟(109/L)": 0.05,
        "IG％": 1.9
    },
    "淋巴类别": {
        "Blasts/Abn Ly": 0.0,
        "Atypical": 0.0,
        "Atypical.1": 140.0,
        "Blasts": 180.0,
        "Abn Ly": 0.0
    },
    "血常规通道参数": {
        "WNR-X": 170.6,
        "WNR-Y": 102.2,
        "WNR-Z": 87.9,
        "WPC-X": 70.3,
        "WPC-Y": 161.6,
        "WPC-Z": 84.2,
        "HFLC%": 1.5,
        "WBC": 2.64,
        "NE-SSC": 141.4,
        "NE-SFL": 43.5,
        "NE-FSC": 77.1,
        "LY-X": 75.8,
        "LY-Y": 64.5,
        "LY-Z": 55.7,
        "MO-X": 102.2,
        "MO-Y": 105.1,
        "MO-Z": 71.3,
        "NE-WX": 417.0,
        "NE-WY": 759.0,
        "NE-WZ": 817.0,
        "LY-WX": 607.0,
        "LY-WY": 946.0,
        "LY-WZ": 610.0,
        "MO-WX": 479.0,
        "MO-WY": 980.0,
        "MO-WZ": 911.0
    },
    "镜检": 9,
    "label": 0
}