{
    "基础信息": {
        "住院号": 609871.0,
        "条码号": 21030830500.0,
        "序号": 1298.0
    },
    "图片路径": "../acute_arms/1298.png",
    "临床": null,
    "生化": null,
    "血常规报告参数": {
        "性别(男1女2）": 1.0,
        "年龄": 6.1,
        "WBC(109/L)": 124.32,
        "RBC(1012/L)": 2.8,
        "HGB(g/L)": 74.0,
        "HCT(％）": 23.6,
        "MCV(fL)": 84.3,
        "MCH(pg)": 26.4,
        "MCHC(g/L)": 314.0,
        "PLT(109/L)": 65.0,
        "RDW-SD(fL)": 46.7,
        "RDW-CV(％）": 16.0,
        "PDW（fL)": 8.6,
        "MPV(fL)": 9.2,
        "P-LCR(％）": 21.3,
        "PCT(％）": 0.05,
        "NRBC﹟(109/L)": 0.27,
        "NRBC％（/100WBC)": 0.2,
        "NEUT％": 3.7,
        "LYMPH％": 93.5,
        "MONO％": 2.7,
        "EO％": 0.0,
        "BASO％": 0.1,
        "IG﹟(109/L)": 0.38,
        "IG％": 0.3
    },
    "淋巴类别": {
        "Blasts/Abn Ly": 0.0,
        "Atypical": 0.0,
        "Atypical.1": 20.0,
        "Blasts": 0.0,
        "Abn Ly": 300.0
    },
    "血常规通道参数": {
        "WNR-X": 175.5,
        "WNR-Y": 93.2,
        "WNR-Z": 88.0,
        "WPC-X": 64.5,
        "WPC-Y": 173.4,
        "WPC-Z": 83.4,
        "HFLC%": 0.2,
        "WBC": 124.32,
        "NE-SSC": 151.0,
        "NE-SFL": 43.2,
        "NE-FSC": 85.2,
        "LY-X": 83.7,
        "LY-Y": 59.7,
        "LY-Z": 59.9,
        "MO-X": 105.6,
        "MO-Y": 98.5,
        "MO-Z": 65.2,
        "NE-WX": 490.0,
        "NE-WY": 995.0,
        "NE-WZ": 704.0,
        "LY-WX": 430.0,
        "LY-WY": 870.0,
        "LY-WZ": 551.0,
        "MO-WX": 246.0,
        "MO-WY": 1147.0,
        "MO-WZ": 1180.0
    },
    "镜检": 54,
    "label": 0
}