{
    "基础信息": {
        "住院号": 457737,
        "条码号": 20506592900,
        "序号": 3139
    },
    "图片路径": "../disease_arms/3139.png",
    "临床": {
        "发热": 1,
        "关节及骨骼痛": 0,
        "出血": 0,
        "贫血": 0,
        "器官肿大": 1,
        "中枢神经系统症状": 0,
        "腹痛": 0,
        "咳嗽": 1,
        "皮疹": 0
    },
    "生化": {
        "乳酸脱氢酶LDH": 939.0,
        "铁蛋白Fer": 763.32
    },
    "血常规报告参数": {
        "性别(男1女2）": 1.0,
        "年龄": 4.8,
        "WBC(109/L)": 56.41,
        "RBC(1012/L)": 3.92,
        "HGB(g/L)": 110.0,
        "HCT(％）": 33.1,
        "MCV(fL)": 84.4,
        "MCH(pg)": 28.1,
        "MCHC(g/L)": 332.0,
        "PLT(109/L)": 236.0,
        "RDW-SD(fL)": 44.5,
        "RDW-CV(％）": 14.6,
        "PDW（fL)": 10.7,
        "MPV(fL)": 10.1,
        "P-LCR(％）": 24.8,
        "PCT(％）": 0.24,
        "NRBC﹟(109/L)": 0.01,
        "NRBC％（/100WBC)": 0.0,
        "NEUT％": 16.5,
        "LYMPH％": 64.583786,
        "MONO％": 7.2346845,
        "EO％": 0.0,
        "BASO％": 1.2,
        "IG﹟(109/L)": 0.42,
        "IG％": 0.7
    },
    "淋巴类别": {
        "Blasts/Abn Ly": 300.0,
        "Atypical": 300.0,
        "Atypical.1": 300.0,
        "Blasts": 0.0,
        "Abn Ly": 300.0
    },
    "血常规通道参数": {
        "WNR-X": 171.6,
        "WNR-Y": 108.3,
        "WNR-Z": 96.7,
        "WPC-X": 76.8,
        "WPC-Y": 168.7,
        "WPC-Z": 93.2,
        "HFLC%": 4.3,
        "WBC": 56.26,
        "NE-SSC": 150.0,
        "NE-SFL": 46.9,
        "NE-FSC": 78.4,
        "LY-X": 83.4,
        "LY-Y": 77.9,
        "LY-Z": 58.9,
        "MO-X": 107.2,
        "MO-Y": 140.5,
        "MO-Z": 66.0,
        "NE-WX": 333.0,
        "NE-WY": 662.0,
        "NE-WZ": 778.0,
        "LY-WX": 491.0,
        "LY-WY": 1284.0,
        "LY-WZ": 645.0,
        "MO-WX": 345.0,
        "MO-WY": 740.0,
        "MO-WZ": 863.0
    },
    "镜检": 11,
    "label": 2
}